fastbox/VARS.py
fastbox/__init__.py
fastbox/models.py
fastbox/portfolio.py
fastbox/risk.py
fastbox/signal.py
fastbox/strategy.py
fastbox/data/__init__.py
fastbox/data/futures.py
fastbox/data/futuresoptions.py
fastbox/data/index.py
fastbox/data/indexoptions.py
fastbox/data/shibor.py
fastbox/data/stocks.py
fastbox/pydantic/__init__.py
fastbox/pydantic/models.py
fastbox/utils/__init__.py
fastbox/utils/utils.py
fastbox/utils/utils_plotting.py
fastbox-0.1b1.dist-info/METADATA
fastbox-0.1b1.dist-info/WHEEL
fastbox-0.1b1.dist-info/top_level.txt
fastbox-0.1b1.dist-info/RECORD
